setup.cfg
setup.py
preprocessing_sg/__init__.py
preprocessing_sg/data_preprocessing.py
preprocessing_sg.egg-info/PKG-INFO
preprocessing_sg.egg-info/SOURCES.txt
preprocessing_sg.egg-info/dependency_links.txt
preprocessing_sg.egg-info/not-zip-safe
preprocessing_sg.egg-info/top_level.txt