Metadata-Version: 1.0
Name: preprocessing-sg
Version: 0.0
Summary: Data Processing Functions
Home-page: UNKNOWN
Author: UNKNOWN
Author-email: sgantayat9@gmail.com
License: UNKNOWN
Platform: UNKNOWN
